strup/__init__.py
strup/unpack.py
strup-1.0.0.dist-info/LICENSE
strup-1.0.0.dist-info/METADATA
strup-1.0.0.dist-info/WHEEL
strup-1.0.0.dist-info/entry_points.txt
strup-1.0.0.dist-info/top_level.txt
strup-1.0.0.dist-info/zip-safe
strup-1.0.0.dist-info/RECORD
