Metadata-Version: 2.1
Name: strup
Version: 1.0.0
Summary: A package for unpacking int, float, string and bool objects from a text string.
Home-page: https://github.com/jeblohe/strup
Author: Jens B. Helmers
Author-email: jens.bloch.helmers@gmail.com
License: MIT
Project-URL: Documentation, https://strup.readthedocs.io/
Project-URL: Bug Tracker, https://github.com/jeblohe/strup/issues
Project-URL: Source Code, https://github.com/jeblohe/strup/
Keywords: text processing
Platform: UNKNOWN
Classifier: Development Status :: 5 - Production/Stable
Classifier: Intended Audience :: Developers
Classifier: Intended Audience :: Education
Classifier: Intended Audience :: End Users/Desktop
Classifier: Intended Audience :: Financial and Insurance Industry
Classifier: Intended Audience :: Information Technology
Classifier: Intended Audience :: Manufacturing
Classifier: Intended Audience :: Other Audience
Classifier: Intended Audience :: Science/Research
Classifier: Intended Audience :: System Administrators
Classifier: Intended Audience :: Telecommunications Industry
Classifier: Topic :: Text Processing
Classifier: License :: OSI Approved :: MIT License
Classifier: Programming Language :: Python :: 2.7
Classifier: Programming Language :: Python :: 3.4
Classifier: Programming Language :: Python :: 3.5
Classifier: Programming Language :: Python :: 3.6
Classifier: Programming Language :: Python :: 3.7
Classifier: Programming Language :: Python :: 3.8
Classifier: Programming Language :: Python :: 3.9
Requires-Python: >=2.7, !=3.0.*, !=3.1.*, !=3.2.*, !=3.3.*, <4
Provides-Extra: dev
Requires-Dist: pytest (>=5.1) ; extra == 'dev'
Requires-Dist: pytest-cov ; extra == 'dev'
Requires-Dist: coverage ; extra == 'dev'
Requires-Dist: black ; extra == 'dev'
Requires-Dist: coveralls ; extra == 'dev'
Provides-Extra: test
Requires-Dist: pytest (>=4.6) ; extra == 'test'
